{"metadata": {"nodeCount": 20, "edgeCount": 17, "stepCount": 8, "rootGoalIds": ["_uniq.290.6", "_uniq.1156.3951", "_uniq.1156.6870"], "leafGoalIds": ["_uniq.1156.5587", "_uniq.1156.6883", "_uniq.1156.6884", "_uniq.290.27"], "openLeafGoalIds": ["_uniq.1156.5587"], "solvedGoalIds": ["_uniq.1156.6883", "_uniq.1156.6884", "_uniq.290.27"], "sourcePath": "/Users/glebsokolovski/Desktop/UNI/lean-visualiser/ProofTracer/TestInput.lean", "declarations": [{"kind": "theorem", "name": "two_dvd_of_sq", "statement": "{n : ℕ} (h : 2 ∣ n ^ 2) : 2 ∣ n", "header": "theorem two_dvd_of_sq {n : ℕ} (h : 2 ∣ n ^ 2) : 2 ∣ n", "startLine": 6, "endLine": 6, "rootGoalId": "_uniq.290.6", "stepIndex": 0}, {"kind": "theorem", "name": "sqrt2_irrational", "statement": "(p q : ℤ) (hq : q ≠ 0) (hcop : Int.gcd p q = 1) (heq : p ^ 2 = 2 * q ^ 2) : False", "header": "theorem sqrt2_irrational (p q : ℤ) (hq : q ≠ 0) (hcop : Int.gcd p q = 1) (heq : p ^ 2 = 2 * q ^ 2) : False", "startLine": 12, "endLine": 14, "rootGoalId": "_uniq.1156.3951", "stepIndex": 2}], "primaryDeclaration": {"kind": "theorem", "name": "two_dvd_of_sq", "statement": "{n : ℕ} (h : 2 ∣ n ^ 2) : 2 ∣ n", "header": "theorem two_dvd_of_sq {n : ℕ} (h : 2 ∣ n ^ 2) : 2 ∣ n", "startLine": 6, "endLine": 6, "rootGoalId": "_uniq.290.6", "stepIndex": 0}}, "nodes": [{"id": "_uniq.290.6", "kind": "goal", "label": "2 ∣ n", "data": {"goalId": "_uniq.290.6", "target": "2 ∣ n", "context": [{"userName": "n", "type": "ℕ"}, {"userName": "h", "type": "2 ∣ n ^ 2"}], "declaration": {"kind": "theorem", "name": "two_dvd_of_sq", "statement": "{n : ℕ} (h : 2 ∣ n ^ 2) : 2 ∣ n", "header": "theorem two_dvd_of_sq {n : ℕ} (h : 2 ∣ n ^ 2) : 2 ∣ n", "startLine": 6, "endLine": 6, "rootGoalId": "_uniq.290.6", "stepIndex": 0}}}, {"id": "_uniq.290.27", "kind": "goal", "label": "2 ∣ n", "data": {"goalId": "_uniq.290.27", "target": "2 ∣ n", "context": [{"userName": "n", "type": "ℕ"}, {"userName": "h", "type": "2 ∣ n ^ 2"}, {"userName": "h2", "type": "Nat.Prime 2"}]}}, {"id": "tactic:0", "kind": "tactic", "label": "have h2 : Nat.Prime 2 := Nat.prime_iff.mpr ⟨by norm_num, by omega⟩", "data": {"stepIndex": 0, "tacticText": "have h2 : Nat.Prime 2 := Nat.prime_iff.mpr ⟨by norm_num, by omega⟩", "tacticKind": "have", "rawTactic": "(Tactic.tacticSeq\n (Tactic.tacticSeq1Indented\n  [(Tactic.tacticHave__\n    \"have\"\n    (Term.letConfig [])\n    (Term.letDecl\n     (Term.letIdDecl\n      (Term.letId `h2)\n      []\n      [(Term.typeSpec \":\" (Term.app `Nat.Prime [(num \"2\")]))]\n      \":=\"\n      (Term.app\n       `Nat.prime_iff.mpr\n       [(Term.anonymousCtor\n         \"⟨\"\n         [(Term.byTactic\n           \"by\"\n           (Tactic.tacticSeq\n            (Tactic.tacticSeq1Indented [(Mathlib.Tactic.normNum \"norm_num\" (Tactic.optConfig []) [] [] [])])))\n          \",\"\n          (Term.byTactic\n           \"by\"\n           (Tactic.tacticSeq (Tactic.tacticSeq1Indented [(Tactic.omega \"omega\" (Tactic.optConfig []))])))]\n         \"⟩\")]))))]))", "focusedGoalId": "_uniq.290.6", "preGoals": ["_uniq.290.6"], "postGoals": ["_uniq.290.27"]}}, {"id": "tactic:1", "kind": "tactic", "label": "exact\n    (h2.dvd_of_dvd_pow h)\n      -- Main theorem: √2 is irrational\n      -- Equivalently: there are no coprime integers p, q with p^2 = 2 * q^2\n      ", "data": {"stepIndex": 1, "tacticText": "exact\n    (h2.dvd_of_dvd_pow h)\n      -- Main theorem: √2 is irrational\n      -- Equivalently: there are no coprime integers p, q with p^2 = 2 * q^2\n      ", "tacticKind": "exact", "rawTactic": "(Tactic.tacticSeq\n (Tactic.tacticSeq1Indented\n  [(Tactic.exact\n    \"exact\"\n    (Term.paren (Term.hygienicLParen \"(\" (hygieneInfo `[anonymous])) (Term.app `h2.dvd_of_dvd_pow [`h]) \")\"))]))", "focusedGoalId": "_uniq.290.27", "preGoals": ["_uniq.290.27"], "postGoals": []}}, {"id": "_uniq.290.27:solved", "kind": "terminal", "label": "solved", "data": {"goalId": "_uniq.290.27", "status": "solved"}}, {"id": "_uniq.1156.3951", "kind": "goal", "label": "2 ∣ q ^ 2", "data": {"goalId": "_uniq.1156.3951", "target": "2 ∣ q ^ 2", "context": [{"userName": "p", "type": "ℤ"}, {"userName": "q", "type": "ℤ"}, {"userName": "hq", "type": "q ≠ 0"}, {"userName": "hcop", "type": "p.gcd q = 1"}, {"userName": "heq", "type": "p ^ 2 = 2 * q ^ 2"}, {"userName": "hdvd_p2", "type": "2 ∣ p ^ 2"}, {"userName": "hprime2", "type": "Prime 2"}, {"userName": "k", "type": "ℤ"}, {"userName": "hk", "type": "p = 2 * k"}], "declaration": {"kind": "theorem", "name": "sqrt2_irrational", "statement": "(p q : ℤ) (hq : q ≠ 0) (hcop : Int.gcd p q = 1) (heq : p ^ 2 = 2 * q ^ 2) : False", "header": "theorem sqrt2_irrational (p q : ℤ) (hq : q ≠ 0) (hcop : Int.gcd p q = 1) (heq : p ^ 2 = 2 * q ^ 2) : False", "startLine": 12, "endLine": 14, "rootGoalId": "_uniq.1156.3951", "stepIndex": 2}}}, {"id": "_uniq.1156.3960", "kind": "goal", "label": "q ^ 2 = 2 * (2 * k ^ 2)", "data": {"goalId": "_uniq.1156.3960", "target": "q ^ 2 = 2 * (2 * k ^ 2)", "context": [{"userName": "p", "type": "ℤ"}, {"userName": "q", "type": "ℤ"}, {"userName": "hq", "type": "q ≠ 0"}, {"userName": "hcop", "type": "p.gcd q = 1"}, {"userName": "heq", "type": "p ^ 2 = 2 * q ^ 2"}, {"userName": "hdvd_p2", "type": "2 ∣ p ^ 2"}, {"userName": "hprime2", "type": "Prime 2"}, {"userName": "k", "type": "ℤ"}, {"userName": "hk", "type": "p = 2 * k"}]}}, {"id": "tactic:2", "kind": "tactic", "label": "use 2 * k ^ 2", "data": {"stepIndex": 2, "tacticText": "use 2 * k ^ 2", "tacticKind": "use", "rawTactic": "(Tactic.tacticSeq\n (Tactic.tacticSeq1Indented\n  [(Mathlib.Tactic.useSyntax \"use\" [] (group) [(«term_*_» (num \"2\") \"*\" («term_^_» `k \"^\" (num \"2\")))])]))", "focusedGoalId": "_uniq.1156.3951", "preGoals": ["_uniq.1156.3951"], "postGoals": ["_uniq.1156.3960"]}}, {"id": "_uniq.1156.4332", "kind": "goal", "label": "q ^ 2 = 2 * (2 * k ^ 2)", "data": {"goalId": "_uniq.1156.4332", "target": "q ^ 2 = 2 * (2 * k ^ 2)", "context": [{"userName": "p", "type": "ℤ"}, {"userName": "q", "type": "ℤ"}, {"userName": "hq", "type": "q ≠ 0"}, {"userName": "hcop", "type": "p.gcd q = 1"}, {"userName": "hdvd_p2", "type": "2 ∣ p ^ 2"}, {"userName": "hprime2", "type": "Prime 2"}, {"userName": "k", "type": "ℤ"}, {"userName": "heq", "type": "(2 * k) ^ 2 = 2 * q ^ 2"}, {"userName": "hk", "type": "p = 2 * k"}]}}, {"id": "tactic:3", "kind": "tactic", "label": "rw [hk] at heq", "data": {"stepIndex": 3, "tacticText": "rw [hk] at heq", "tacticKind": "rw", "rawTactic": "(Tactic.tacticSeq\n (Tactic.tacticSeq1Indented\n  [(Tactic.rwSeq\n    \"rw\"\n    (Tactic.optConfig [])\n    (Tactic.rwRuleSeq \"[\" [(Tactic.rwRule [] `hk)] \"]\")\n    [(Tactic.location \"at\" (Tactic.locationHyp [`heq]))])]))", "focusedGoalId": "_uniq.1156.3960", "preGoals": ["_uniq.1156.3960"], "postGoals": ["_uniq.1156.4332"]}}, {"id": "_uniq.1156.5587", "kind": "goal", "label": "q ^ 2 = k ^ 2 * 4", "data": {"goalId": "_uniq.1156.5587", "target": "q ^ 2 = k ^ 2 * 4", "context": [{"userName": "p", "type": "ℤ"}, {"userName": "q", "type": "ℤ"}, {"userName": "hq", "type": "q ≠ 0"}, {"userName": "hcop", "type": "p.gcd q = 1"}, {"userName": "hdvd_p2", "type": "2 ∣ p ^ 2"}, {"userName": "hprime2", "type": "Prime 2"}, {"userName": "k", "type": "ℤ"}, {"userName": "hk", "type": "p = 2 * k"}, {"userName": "heq", "type": "k ^ 2 * 4 = q ^ 2 * 2"}]}}, {"id": "tactic:4", "kind": "tactic", "label": "ring_nf at heq ⊢", "data": {"stepIndex": 4, "tacticText": "ring_nf at heq ⊢", "tacticKind": "ring_nf", "rawTactic": "(Tactic.tacticSeq\n (Tactic.tacticSeq1Indented\n  [(Mathlib.Tactic.RingNF.ringNF\n    \"ring_nf\"\n    []\n    (Tactic.optConfig [])\n    [(Tactic.location \"at\" (Tactic.locationHyp [`heq (Tactic.locationType (patternIgnore (token.«⊢» \"⊢\")))]))])]))", "focusedGoalId": "_uniq.1156.4332", "preGoals": ["_uniq.1156.4332"], "postGoals": ["_uniq.1156.5587"]}}, {"id": "_uniq.1156.6870", "kind": "goal", "label": "2 ∣ p.gcd q", "data": {"goalId": "_uniq.1156.6870", "target": "2 ∣ p.gcd q", "context": [{"userName": "p", "type": "ℤ"}, {"userName": "q", "type": "ℤ"}, {"userName": "hq", "type": "q ≠ 0"}, {"userName": "hcop", "type": "p.gcd q = 1"}, {"userName": "heq", "type": "p ^ 2 = 2 * q ^ 2"}, {"userName": "hdvd_p2", "type": "2 ∣ p ^ 2"}, {"userName": "hprime2", "type": "Prime 2"}, {"userName": "k", "type": "ℤ"}, {"userName": "hk", "type": "p = 2 * k"}, {"userName": "hdvd_q2", "type": "2 ∣ q ^ 2"}, {"userName": "hdvd_q", "type": "2 ∣ q"}]}}, {"id": "_uniq.1156.6883", "kind": "goal", "label": "↑2 ∣ p", "data": {"goalId": "_uniq.1156.6883", "target": "↑2 ∣ p", "context": [{"userName": "p", "type": "ℤ"}, {"userName": "q", "type": "ℤ"}, {"userName": "hq", "type": "q ≠ 0"}, {"userName": "hcop", "type": "p.gcd q = 1"}, {"userName": "heq", "type": "p ^ 2 = 2 * q ^ 2"}, {"userName": "hdvd_p2", "type": "2 ∣ p ^ 2"}, {"userName": "hprime2", "type": "Prime 2"}, {"userName": "k", "type": "ℤ"}, {"userName": "hk", "type": "p = 2 * k"}, {"userName": "hdvd_q2", "type": "2 ∣ q ^ 2"}, {"userName": "hdvd_q", "type": "2 ∣ q"}]}}, {"id": "_uniq.1156.6884", "kind": "goal", "label": "↑2 ∣ q", "data": {"goalId": "_uniq.1156.6884", "target": "↑2 ∣ q", "context": [{"userName": "p", "type": "ℤ"}, {"userName": "q", "type": "ℤ"}, {"userName": "hq", "type": "q ≠ 0"}, {"userName": "hcop", "type": "p.gcd q = 1"}, {"userName": "heq", "type": "p ^ 2 = 2 * q ^ 2"}, {"userName": "hdvd_p2", "type": "2 ∣ p ^ 2"}, {"userName": "hprime2", "type": "Prime 2"}, {"userName": "k", "type": "ℤ"}, {"userName": "hk", "type": "p = 2 * k"}, {"userName": "hdvd_q2", "type": "2 ∣ q ^ 2"}, {"userName": "hdvd_q", "type": "2 ∣ q"}]}}, {"id": "tactic:5", "kind": "tactic", "label": "apply Int.dvd_gcd", "data": {"stepIndex": 5, "tacticText": "apply Int.dvd_gcd", "tacticKind": "apply", "rawTactic": "(Tactic.tacticSeq (Tactic.tacticSeq1Indented [(Tactic.apply \"apply\" `Int.dvd_gcd)]))", "focusedGoalId": "_uniq.1156.6870", "preGoals": ["_uniq.1156.6870"], "postGoals": ["_uniq.1156.6883", "_uniq.1156.6884"]}}, {"id": "tactic:6", "kind": "tactic", "label": "exact_mod_cast hdvd_p", "data": {"stepIndex": 6, "tacticText": "exact_mod_cast hdvd_p", "tacticKind": "exact", "rawTactic": "(Tactic.tacticSeq (Tactic.tacticSeq1Indented [(Tactic.tacticExact_mod_cast_ \"exact_mod_cast\" `hdvd_p)]))", "focusedGoalId": "_uniq.1156.6883", "preGoals": ["_uniq.1156.6883"], "postGoals": []}}, {"id": "_uniq.1156.6883:solved", "kind": "terminal", "label": "solved", "data": {"goalId": "_uniq.1156.6883", "status": "solved"}}, {"id": "tactic:7", "kind": "tactic", "label": "exact_mod_cast hdvd_q", "data": {"stepIndex": 7, "tacticText": "exact_mod_cast hdvd_q", "tacticKind": "exact", "rawTactic": "(Tactic.tacticSeq (Tactic.tacticSeq1Indented [(Tactic.tacticExact_mod_cast_ \"exact_mod_cast\" `hdvd_q)]))", "focusedGoalId": "_uniq.1156.6884", "preGoals": ["_uniq.1156.6884"], "postGoals": []}}, {"id": "_uniq.1156.6884:solved", "kind": "terminal", "label": "solved", "data": {"goalId": "_uniq.1156.6884", "status": "solved"}}], "edges": [{"source": "_uniq.290.6", "target": "tactic:0", "kind": "applies", "data": {"stepIndex": 0}}, {"source": "tactic:0", "target": "_uniq.290.27", "kind": "produces", "data": {"stepIndex": 0, "childIndex": 0}}, {"source": "_uniq.290.27", "target": "tactic:1", "kind": "applies", "data": {"stepIndex": 1}}, {"source": "tactic:1", "target": "_uniq.290.27:solved", "kind": "resolves", "data": {"stepIndex": 1}}, {"source": "_uniq.1156.3951", "target": "tactic:2", "kind": "applies", "data": {"stepIndex": 2}}, {"source": "tactic:2", "target": "_uniq.1156.3960", "kind": "produces", "data": {"stepIndex": 2, "childIndex": 0}}, {"source": "_uniq.1156.3960", "target": "tactic:3", "kind": "applies", "data": {"stepIndex": 3}}, {"source": "tactic:3", "target": "_uniq.1156.4332", "kind": "produces", "data": {"stepIndex": 3, "childIndex": 0}}, {"source": "_uniq.1156.4332", "target": "tactic:4", "kind": "applies", "data": {"stepIndex": 4}}, {"source": "tactic:4", "target": "_uniq.1156.5587", "kind": "produces", "data": {"stepIndex": 4, "childIndex": 0}}, {"source": "_uniq.1156.6870", "target": "tactic:5", "kind": "applies", "data": {"stepIndex": 5}}, {"source": "tactic:5", "target": "_uniq.1156.6883", "kind": "produces", "data": {"stepIndex": 5, "childIndex": 0}}, {"source": "tactic:5", "target": "_uniq.1156.6884", "kind": "produces", "data": {"stepIndex": 5, "childIndex": 1}}, {"source": "_uniq.1156.6883", "target": "tactic:6", "kind": "applies", "data": {"stepIndex": 6}}, {"source": "tactic:6", "target": "_uniq.1156.6883:solved", "kind": "resolves", "data": {"stepIndex": 6}}, {"source": "_uniq.1156.6884", "target": "tactic:7", "kind": "applies", "data": {"stepIndex": 7}}, {"source": "tactic:7", "target": "_uniq.1156.6884:solved", "kind": "resolves", "data": {"stepIndex": 7}}]}
